.gitignore
LICENSE
MANIFEST.in
README.rst
setup.py
widget_party/__init__.py
widget_party/__init__.pyc
widget_party/widgets.py
widget_party.egg-info/PKG-INFO
widget_party.egg-info/SOURCES.txt
widget_party.egg-info/dependency_links.txt
widget_party.egg-info/requires.txt
widget_party.egg-info/top_level.txt
widget_party/static/widgets/assignment/assignment.css
widget_party/static/widgets/assignment/assignment.html
widget_party/static/widgets/assignment/assignment.js
widget_party/static/widgets/builderlist/builderlist.css
widget_party/static/widgets/builderlist/builderlist.html
widget_party/static/widgets/builderlist/builderlist.js
widget_party/static/widgets/buildstatus/buildstatus.css
widget_party/static/widgets/buildstatus/buildstatus.html
widget_party/static/widgets/buildstatus/buildstatus.js
widget_party/static/widgets/commitlist/commitlist.css
widget_party/static/widgets/commitlist/commitlist.html
widget_party/static/widgets/commitlist/commitlist.js
widget_party/static/widgets/fatlist/fatlist.css
widget_party/static/widgets/fatlist/fatlist.html
widget_party/static/widgets/fatlist/fatlist.js
widget_party/static/widgets/fatnumber/fatnumber.css
widget_party/static/widgets/fatnumber/fatnumber.html
widget_party/static/widgets/fatnumber/fatnumber.js
widget_party/static/widgets/informednumber/informednumber.css
widget_party/static/widgets/informednumber/informednumber.html
widget_party/static/widgets/informednumber/informednumber.js
widget_party/static/widgets/linklist/linklist.css
widget_party/static/widgets/linklist/linklist.html
widget_party/static/widgets/linklist/linklist.js
widget_party/static/widgets/sizednumber/sizednumber.css
widget_party/static/widgets/sizednumber/sizednumber.html
widget_party/static/widgets/sizednumber/sizednumber.js
widget_party/static/widgets/skinnylist/skinnylist.css
widget_party/static/widgets/skinnylist/skinnylist.html
widget_party/static/widgets/skinnylist/skinnylist.js
widgets/assignment/assignment.css
widgets/assignment/assignment.html
widgets/assignment/assignment.js
widgets/builderlist/builderlist.css
widgets/builderlist/builderlist.html
widgets/builderlist/builderlist.js
widgets/buildstatus/buildstatus.css
